geo_prepper/__init__.py
geo_prepper-0.1.data/scripts/geo_prepper
geo_prepper-0.1.dist-info/LICENSE
geo_prepper-0.1.dist-info/METADATA
geo_prepper-0.1.dist-info/WHEEL
geo_prepper-0.1.dist-info/top_level.txt
geo_prepper-0.1.dist-info/RECORD
