Metadata-Version: 2.1
Name: geo-prepper
Version: 0.1
Summary: GEO submission prepper
Home-page: http://github.com/NICHD-BSPC/geo_prepper
Author: Apratim Mitra
Author-email: apratim.mitra@nih.gov
License: GNU GPLv3
Platform: UNKNOWN
Classifier: License :: OSI Approved :: GNU General Public License (GPL)
Classifier: Operating System :: OS Independent
Classifier: Programming Language :: Python :: 3
Requires-Dist: pandas
Requires-Dist: pyyaml
